pymedphys_monomanage/__init__.py
pymedphys_monomanage/_install_requires.py
pymedphys_monomanage/_version.py
pymedphys_monomanage/app/__init__.py
pymedphys_monomanage/app/api.py
pymedphys_monomanage/app/wheels.py
pymedphys_monomanage/clean/__init__.py
pymedphys_monomanage/clean/core.py
pymedphys_monomanage/clean/formatters.py
pymedphys_monomanage/docs/__init__.py
pymedphys_monomanage/docs/api.py
pymedphys_monomanage/docs/graphs.py
pymedphys_monomanage/draw/__init__.py
pymedphys_monomanage/draw/api.py
pymedphys_monomanage/draw/directories.py
pymedphys_monomanage/draw/files.py
pymedphys_monomanage/draw/packages.py
pymedphys_monomanage/draw/utilities.py
pymedphys_monomanage/parse/__init__.py
pymedphys_monomanage/parse/imports.py
pymedphys_monomanage/propagate/__init__.py
pymedphys_monomanage/propagate/dependencies.py
pymedphys_monomanage/propagate/versions.py
pymedphys_monomanage/tree/__init__.py
pymedphys_monomanage/tree/build.py
pymedphys_monomanage/tree/check.py
pymedphys_monomanage-0.11.0.dist-info/LICENSE-AGPL-3.0-or-later
pymedphys_monomanage-0.11.0.dist-info/LICENSE-Apache-2.0
pymedphys_monomanage-0.11.0.dist-info/METADATA
pymedphys_monomanage-0.11.0.dist-info/WHEEL
pymedphys_monomanage-0.11.0.dist-info/top_level.txt
pymedphys_monomanage-0.11.0.dist-info/RECORD
